{
  "answers": [
    {
      "answerId": 800056538,
      "title": "为什么带土一直没尽早夺回卡卡西的左眼呢？",
      "questionId": "336942453",
      "authorName": "即墨烟花",
      "authorId": "c08ea38df36808e115dd70008170841f",
      "content": "<p>有了双神威</p><p>就没太子啥事儿了123345678978912ew133456789</p><p>剧情需要</p>",
      "upVoteNum": 0,
      "createTime": 1567830393411,
      "approve": 1,
      "type": "scrapy.update-answers"
    },
    {
      "answerId": 799345780,
      "title": "为什么带土一直没尽早夺回卡卡西的左眼呢？",
      "questionId": "336942453",
      "authorName": "一条椒盐烤鱼",
      "authorId": "cb41bfcf4dfdab46d7f7120e2abc8860",
      "content": "<p>我认为是带土不忍心：</p><p>有三点，第一点，带土理论上想杀谁就杀谁，夜晚夜深人静神威抹脖子，想要夺回其实很简单。</p><p>第二点，在地狱带土那个时间段，卡卡西晕了，带土把除了他以外的人都杀了，这段时间想杀就杀，想夺眼就夺眼，但是他没有。</p><p>第三点，带土在发动月之眼计划，经典台词：英雄不用站在慰灵碑前忏悔。到我这里来吧！</p>",
      "upVoteNum": 0,
      "createTime": 1567830393397,
      "approve": 2,
      "type": "scrapy.update-answers"
    },
    {
      "answerId": 574467609,
      "title": "为什么很多司机不办ETC？",
      "questionId": "295719685",
      "authorName": "李东升",
      "authorId": "e4997ebce49008be8bba2164350e1c22",
      "content": "<p>我觉得对大多数人来说是投入产出比不够高。</p><p>确实ETC非常好用，我有一年多每两天北京天津往返，有极其偶尔的ETC排队的意外情况，但99%以上都是只需要减速不需要停车的通过，人工就不行了，有一半是需要排队的。</p><p>现在很多银行推出的ETC都已经免费了，用信用卡还不用提前存钱，很方便。但你想拥有ETC，需要申请（1），通过后，收到银行寄来的速通卡，去速通公司贴标签（2），因为ETC跟车绑定，如果换车，你需要再去速通公司做变更（3），基于以上的1、2、3，很多不是经常跑高速的人就不会这么一趟一趟跑了。对他们来说，1+2+3跑三趟带来的收益是一年跑两次高速节约的5分钟。</p><p>当然，经常跑高速的人是会忍受这几趟去办一个ETC，但这里面还有开的别人名下的车、公司车、需要发票等不能办的情况。</p><p>还有一点，ETC各地各家的流程和规定各异，用户还有搞清楚办理流程的时间成本，没有ETC的人在高速排队的时候肯定羡慕有ETC的人，但是高速上不会有办ETC的地方，羡慕归羡慕，回家以后要不就忘了，要不突然发现不知道怎么办ETC，花了半个小时才搞清楚上哪办，再一琢磨这么麻烦就算了。如果跟注册支付宝一样，在收费站竖个二维码，排队的时候扫描提交资料，等到家第二天，ETC送到家里了，我估计会有大量用户增加。</p><p>一个彩蛋，京津高速，进京方向，永乐店收费站，如果带了妹子，如果你是信用卡ETC，一定要走最左侧的ETC口，妹子会被你ETC余额几十万惊呆的，什么家庭会在ETC里存几十万，我的天。</p><p>——————-更新一次—————-</p><p>得益于最近国家推广etc到80%的目标，各银行等机构为了抢人，体验好的不是一点点，身边几个朋友多少年不装etc也借此东风申请了，我也又申请了一个，招商银行app里申请，不用预存，不用新开卡，用已有的信用卡，设备免费，邮寄到家自己安装，真香</p><figure data-size=\"normal\"><noscript><img src=\"https://pic3.zhimg.com/50/v2-3bb877058c94e2fb7b1abd9013004ab2_hd.jpg\" data-rawwidth=\"750\" data-rawheight=\"1334\" data-size=\"normal\" data-default-watermark-src=\"https://pic3.zhimg.com/50/v2-7cf2b5d0049d719a4fd789a3c6d9d8aa_hd.jpg\" class=\"origin_image zh-lightbox-thumb\" width=\"750\" data-original=\"https://pic3.zhimg.com/v2-3bb877058c94e2fb7b1abd9013004ab2_r.jpg\"/></noscript><img src=\"data:image/svg+xml;utf8,<svg xmlns='http://www.w3.org/2000/svg' width='750' height='1334'></svg>\" data-rawwidth=\"750\" data-rawheight=\"1334\" data-size=\"normal\" data-default-watermark-src=\"https://pic3.zhimg.com/50/v2-7cf2b5d0049d719a4fd789a3c6d9d8aa_hd.jpg\" class=\"origin_image zh-lightbox-thumb lazy\" width=\"750\" data-original=\"https://pic3.zhimg.com/v2-3bb877058c94e2fb7b1abd9013004ab2_r.jpg\" data-actualsrc=\"https://pic3.zhimg.com/50/v2-3bb877058c94e2fb7b1abd9013004ab2_hd.jpg\"></figure><p></p>",
      "upVoteNum": 592,
      "createTime": 1567694957242,
      "approve": 1,
      "type": "scrapy.update-answers"
    }
  ]
}
